{"players": [{"teamId": 100, "summonerName": "DukeOfJamming", "championId": 235, "summoner1Id": 7, "summoner2Id": 4, "kills": 6, "deaths": 3, "assists": 8, "kda": 4.666666666666667, "item0": 3009, "item1": 3864, "item2": 2055, "item3": 3042, "item4": 6692, "item5": 3086, "totalDamageDealtToChampions": 12726, "visionScore": 66, "individualPosition": "UTILITY"}, {"teamId": 100, "summonerName": "Cargilly", "championId": 22, "summoner1Id": 1, "summoner2Id": 4, "kills": 1, "deaths": 1, "assists": 8, "kda": 9, "item0": 3042, "item1": 6673, "item2": 3091, "item3": 3006, "item4": 2055, "item5": 0, "totalDamageDealtToChampions": 8733, "visionScore": 34, "individualPosition": "BOTTOM"}, {"teamId": 100, "summonerName": "caruana", "championId": 121, "summoner1Id": 11, "summoner2Id": 4, "kills": 4, "deaths": 5, "assists": 12, "kda": 3.2, "item0": 3142, "item1": 3026, "item2": 2031, "item3": 3036, "item4": 6692, "item5": 3158, "totalDamageDealtToChampions": 16165, "visionScore": 31, "individualPosition": "JUNGLE"}, {"teamId": 100, "summonerName": "beddomu", "championId": 39, "summoner1Id": 12, "summoner2Id": 4, "kills": 6, "deaths": 4, "assists": 2, "kda": 2, "item0": 6630, "item1": 2420, "item2": 3047, "item3": 1055, "item4": 6333, "item5": 3153, "totalDamageDealtToChampions": 13407, "visionScore": 16, "individualPosition": "TOP"}, {"teamId": 100, "summonerName": "Disastrously", "championId": 134, "summoner1Id": 14, "summoner2Id": 4, "kills": 14, "deaths": 0, "assists": 8, "kda": 22, "item0": 6655, "item1": 3020, "item2": 3157, "item3": 4628, "item4": 1056, "item5": 4645, "totalDamageDealtToChampions": 35579, "visionScore": 37, "individualPosition": "MIDDLE"}, {"teamId": 200, "summonerName": "DZN Ares", "championId": 875, "summoner1Id": 4, "summoner2Id": 12, "kills": 7, "deaths": 4, "assists": 2, "kda": 2.25, "item0": 3155, "item1": 3181, "item2": 3047, "item3": 6631, "item4": 6333, "item5": 0, "totalDamageDealtToChampions": 18198, "visionScore": 20, "individualPosition": "TOP"}, {"teamId": 200, "summonerName": "time gear", "championId": 221, "summoner1Id": 4, "summoner2Id": 3, "kills": 2, "deaths": 5, "assists": 3, "kda": 1, "item0": 3078, "item1": 3748, "item2": 3006, "item3": 1033, "item4": 3051, "item5": 0, "totalDamageDealtToChampions": 7134, "visionScore": 14, "individualPosition": "BOTTOM"}, {"teamId": 200, "summonerName": "Haiks", "championId": 101, "summoner1Id": 4, "summoner2Id": 7, "kills": 1, "deaths": 4, "assists": 5, "kda": 1.5, "item0": 6655, "item1": 3145, "item2": 3108, "item3": 3020, "item4": 0, "item5": 3853, "totalDamageDealtToChampions": 12361, "visionScore": 52, "individualPosition": "UTILITY"}, {"teamId": 200, "summonerName": "February 14th", "championId": 112, "summoner1Id": 4, "summoner2Id": 12, "kills": 2, "deaths": 9, "assists": 1, "kda": 0.3333333333333333, "item0": 2033, "item1": 6655, "item2": 3157, "item3": 3111, "item4": 3145, "item5": 0, "totalDamageDealtToChampions": 13396, "visionScore": 10, "individualPosition": "MIDDLE"}, {"teamId": 200, "summonerName": "DZN MaxCrisp", "championId": 32, "summoner1Id": 4, "summoner2Id": 11, "kills": 1, "deaths": 9, "assists": 6, "kda": 0.7777777777777778, "item0": 3068, "item1": 1033, "item2": 3047, "item3": 3075, "item4": 1028, "item5": 0, "totalDamageDealtToChampions": 7754, "visionScore": 25, "individualPosition": "JUNGLE"}], "teams": [{"win": true, "teamId": 100}, {"win": false, "teamId": 200}], "index": 90, "gameId": 5838458477, "gameEndTimestamp": 1650838817425}