{"175789990490537985": {"summonerIconId": 5919, "name": "scottproudmoore", "lp": 234, "wins": 4, "losses": 2, "unp": 1200}, "597518016644775963": {"summonerIconId": 5919, "name": "_hwks", "lp": 234, "wins": 3, "losses": 1, "unp": 800}, "181877056924024834": {"summonerIconId": 5143, "name": "rack96", "lp": 233, "wins": 3, "losses": 1, "unp": 800}, "165778185743630336": {"summonerIconId": 539, "name": "garde", "lp": 233, "wins": 2, "losses": 0, "unp": 400}, "238670886306054146": {"summonerIconId": 4570, "name": "tzums", "lp": 217, "wins": 1, "losses": 0, "unp": 200}, "191125877000503297": {"summonerIconId": 5752, "name": "judgeyrocks", "lp": 217, "wins": 3, "losses": 2, "unp": 1000}, "174852377621299203": {"summonerIconId": 5091, "name": "cargilly", "lp": 217, "wins": 2, "losses": 1, "unp": 600}, "321239544991186947": {"summonerIconId": 3161, "name": "otterfuyu", "lp": 216, "wins": 3, "losses": 2, "unp": 1000}, "358610059548164097": {"summonerIconId": 5170, "name": "harthill", "lp": 216, "wins": 2, "losses": 1, "unp": 600}, "240426628952358913": {"summonerIconId": 1116, "name": "smudgyy", "lp": 216, "wins": 1, "losses": 0, "unp": 200}, "370321091668869132": {"summonerIconId": 5751, "name": "shieldtwink", "lp": 216, "wins": 1, "losses": 0, "unp": 200}, "159051189198127105": {"summonerIconId": 691, "name": "dukeofjamming", "lp": 201, "wins": 2, "losses": 2, "unp": 800}, "235855377286037504": {"summonerIconId": 4136, "name": "enixxx", "lp": 200, "wins": 0, "losses": 0, "unp": 0}, "274630483583696898": {"summonerIconId": 1116, "name": "beckla_", "lp": 200, "wins": 0, "losses": 0, "unp": 0}, "206407614899159040": {"summonerIconId": 5292, "name": ".dabis", "lp": 200, "wins": 0, "losses": 0, "unp": 0}, "217391216709468163": {"summonerIconId": 5912, "name": "violet_spore", "lp": 200, "wins": 0, "losses": 0, "unp": 0}, "609152960643072040": {"summonerIconId": 5922, "name": "kezm.", "lp": 200, "wins": 0, "losses": 0, "unp": 0}, "190528181927673856": {"summonerIconId": 10, "name": "AIDAN", "lp": 200, "wins": 0, "losses": 0, "unp": 0}, "265936569058328576": {"summonerIconId": 4638, "name": "healtwink", "lp": 200, "wins": 0, "losses": 0, "unp": 0}, "223935551697321984": {"summonerIconId": 4895, "name": "friend_.", "lp": 199, "wins": 2, "losses": 2, "unp": 800}, "337573402778796035": {"summonerIconId": 3890, "name": "junna.", "lp": 184, "wins": 0, "losses": 1, "unp": 200}, "127003591339802624": {"summonerIconId": 10, "name": "riftmark", "lp": 184, "wins": 0, "losses": 1, "unp": 200}, "325994243363700736": {"summonerIconId": 5294, "name": "imarre", "lp": 167, "wins": 0, "losses": 2, "unp": 400}, "100310669668122624": {"summonerIconId": 3868, "name": "grannyspanner", "lp": 167, "wins": 0, "losses": 2, "unp": 400}, "506606702045429760": {"summonerIconId": 3380, "name": "MDIB", "lp": 166, "wins": 0, "losses": 2, "unp": 400}, "194932912729227264": {"summonerIconId": 5023, "name": "february14th", "lp": 149, "wins": 0, "losses": 3, "unp": 600}, "301821822502961152": {"summonerIconId": 3151, "name": "beddomu", "lp": 133, "wins": 1, "losses": 5, "unp": 1200}}